collective/collectionepilog/__init__.py
collective/collectionepilog/configure.zcml
collective/collectionepilog/dependencies.zcml
collective/collectionepilog/interfaces.py
collective/collectionepilog/permissions.zcml
collective/collectionepilog/profiles.zcml
collective/collectionepilog/testing.py
collective/collectionepilog/behaviors/__init__.py
collective/collectionepilog/behaviors/collection_epilog.py
collective/collectionepilog/behaviors/configure.zcml
collective/collectionepilog/locales/__init__.py
collective/collectionepilog/locales/__main__.py
collective/collectionepilog/locales/collective.collectionepilog.pot
collective/collectionepilog/locales/en/LC_MESSAGES/collective.collectionepilog.po
collective/collectionepilog/profiles/default/browserlayer.xml
collective/collectionepilog/profiles/default/catalog.xml
collective/collectionepilog/profiles/default/controlpanel.xml
collective/collectionepilog/profiles/default/diff_tool.xml
collective/collectionepilog/profiles/default/metadata.xml
collective/collectionepilog/profiles/default/repositorytool.xml
collective/collectionepilog/profiles/default/rolemap.xml
collective/collectionepilog/profiles/default/types.xml
collective/collectionepilog/profiles/default/viewlets.xml
collective/collectionepilog/profiles/default/registry/main.xml
collective/collectionepilog/profiles/default/types/.gitkeep
collective/collectionepilog/profiles/uninstall/browserlayer.xml
collective/collectionepilog/setuphandlers/__init__.py
collective/collectionepilog/tests/__init__.py
collective/collectionepilog/tests/test_behavior_collection_epilog.py
collective/collectionepilog/tests/test_upgrade_step_1001.py
collective/collectionepilog/tests/test_viewlet_collection_epilog.py
collective/collectionepilog/upgrades/1001.zcml
collective/collectionepilog/upgrades/__init__.py
collective/collectionepilog/upgrades/base.py
collective/collectionepilog/upgrades/configure.zcml
collective/collectionepilog/upgrades/v1001.py
collective_collectionepilog-0.1.0a6.dist-info/licenses/LICENSE.GPL
collective_collectionepilog-0.1.0a6.dist-info/licenses/LICENSE.md
collective_collectionepilog-0.1.0a6.dist-info/METADATA
collective_collectionepilog-0.1.0a6.dist-info/WHEEL
collective_collectionepilog-0.1.0a6.dist-info/entry_points.txt
collective_collectionepilog-0.1.0a6.dist-info/top_level.txt
collective_collectionepilog-0.1.0a6.dist-info/RECORD
