Metadata-Version: 2.4
Name: collective-collectionepilog
Version: 0.1.0a6
Summary: Provides a behavior for collections to add epilog RichText field under the collection results.
Author-email: "Maik Derstappen - md@derico.de" <md@derico.de>
Project-URL: Homepage, https://github.com/collective/collective.collectionepilog
Project-URL: PyPI, https://pypi.org/project/collective.collectionepilog
Project-URL: Source, https://github.com/collective/collective.collectionepilog
Project-URL: Tracker, https://github.com/collective/collective.collectionepilog/issues
Keywords: CMS,Plone,Python
Classifier: Development Status :: 3 - Alpha
Classifier: Environment :: Web Environment
Classifier: Framework :: Plone
Classifier: Framework :: Plone :: 6.1
Classifier: Framework :: Plone :: Addon
Classifier: License :: OSI Approved :: GNU General Public License v2 (GPLv2)
Classifier: Operating System :: OS Independent
Classifier: Programming Language :: Python
Classifier: Programming Language :: Python :: 3.13
Classifier: Programming Language :: Python :: 3.12
Requires-Python: >=3.12
License-File: LICENSE.GPL
License-File: LICENSE.md
Requires-Dist: Products.CMFPlone
Requires-Dist: plone.api
Requires-Dist: plone.app.contenttypes
Provides-Extra: test
Requires-Dist: horse-with-no-namespace; extra == "test"
Requires-Dist: plone.app.testing; extra == "test"
Requires-Dist: plone.restapi[test]; extra == "test"
Requires-Dist: pytest; extra == "test"
Requires-Dist: pytest-cov; extra == "test"
Requires-Dist: pytest-plone>=0.5.0; extra == "test"
Dynamic: license-file
